suricat/__init__.py
suricat/beamplots.py
suricat/beams.py
suricat/cabs/__init__.py
suricat/cabs/suricat.yml
suricat/cargo/.persistent_history
suricat/cargo/__init__.py
suricat/cargo/cargo-manifest.yml
suricat/cargo/suricat/Dockerfile.branch-install
suricat/main.py
suricat/recipes/__init__.py
suricat/recipes/init.yml
suricat_beams-0.1.2.dist-info/LICENSE
suricat_beams-0.1.2.dist-info/METADATA
suricat_beams-0.1.2.dist-info/WHEEL
suricat_beams-0.1.2.dist-info/entry_points.txt
suricat_beams-0.1.2.dist-info/RECORD
