Metadata-Version: 2.3
Name: suricat-beams
Version: 0.1.2
Summary: MeerKAT primary beam model handling utilities
License: MIT
Author: Oleg Smirnov
Author-email: osmirnov@gmail.com
Requires-Python: >=3.8,<4.0
Classifier: License :: OSI Approved :: MIT License
Classifier: Programming Language :: Python :: 3
Classifier: Programming Language :: Python :: 3.8
Classifier: Programming Language :: Python :: 3.9
Classifier: Programming Language :: Python :: 3.10
Classifier: Programming Language :: Python :: 3.11
Classifier: Programming Language :: Python :: 3.12
Classifier: Programming Language :: Python :: 3.13
Requires-Dist: astro-tigger-lsm
Requires-Dist: astropy
Requires-Dist: click
Requires-Dist: matplotlib
Requires-Dist: numpy
Requires-Dist: scipy
Requires-Dist: stimela (>=2.0,<3.0)
Requires-Dist: wget
Requires-Dist: xarray-fits
Requires-Dist: zarr (<3)
